{
  "@context": "https://raw.githubusercontent.com/juztamau5/ontology/master/schema/controller.json",
  "@type": "controller",
  "description": {
    "en": "Game Boy Advance is a 32-bit handheld video game console developed by Nintendo."
  },
  "faceButtons": [
    "a",
    "b",
    "down",
    "left",
    "right",
    "select",
    "start",
    "up"
  ],
  "gamePlatform": "http://thegamesdb.net/platform/nintendo-gameboy-advance/",
  "label": {
    "en": "GBA"
  },
  "shoulderButtons": [
    "leftbumper",
    "rightbumper"
  ]
}